supplier_api_tester/__init__.py
supplier_api_tester/cli.py
supplier_api_tester/version.py
supplier_api_tester/v1/__init__.py
supplier_api_tester/v1/cli.py
supplier_api_tester/v1/client.py
supplier_api_tester/v1/decorators.py
supplier_api_tester/v1/exceptions.py
supplier_api_tester/v1/models.py
supplier_api_tester/v1/printer.py
supplier_api_tester/v1/tester.py
supplier_api_tester/v1/version.py
supplier_api_tester/v1/tests/__init__.py
supplier_api_tester/v1/tests/availability_timeslots.py
supplier_api_tester/v1/tests/availability_variants.py
supplier_api_tester/v1/tests/booking.py
supplier_api_tester/v1/tests/product_catalog.py
supplier_api_tester/v1/tests/reservation.py
supplier_api_tester/v1/utils/__init__.py
supplier_api_tester/v1/utils/adapters.py
supplier_api_tester/v1/utils/availability.py
supplier_api_tester/v1/utils/conversions.py
supplier_api_tester/v1/utils/date.py
supplier_api_tester/v1/utils/errors.py
supplier_api_tester/v1/utils/reservation.py
supplier_api_tester/v2/__init__.py
supplier_api_tester/v2/cli.py
supplier_api_tester/v2/client.py
supplier_api_tester/v2/decorators.py
supplier_api_tester/v2/exceptions.py
supplier_api_tester/v2/models.py
supplier_api_tester/v2/printer.py
supplier_api_tester/v2/tester.py
supplier_api_tester/v2/tests/__init__.py
supplier_api_tester/v2/tests/availability_variants.py
supplier_api_tester/v2/tests/booking.py
supplier_api_tester/v2/tests/product_catalog.py
supplier_api_tester/v2/tests/reservation.py
supplier_api_tester/v2/utils/__init__.py
supplier_api_tester/v2/utils/adapters.py
supplier_api_tester/v2/utils/availability.py
supplier_api_tester/v2/utils/catalog.py
supplier_api_tester/v2/utils/conversions.py
supplier_api_tester/v2/utils/date.py
supplier_api_tester/v2/utils/errors.py
supplier_api_tester/v2/utils/reservation.py
supplier_api_tester-2.2.11.data/data/README.md/README.md
supplier_api_tester-2.2.11.data/data/requirements.txt/requirements.txt
supplier_api_tester-2.2.11.dist-info/METADATA
supplier_api_tester-2.2.11.dist-info/WHEEL
supplier_api_tester-2.2.11.dist-info/entry_points.txt
supplier_api_tester-2.2.11.dist-info/top_level.txt
supplier_api_tester-2.2.11.dist-info/RECORD
