Metadata-Version: 2.1
Name: Supplier-API-tester
Version: 2.2.11
Summary: Console tool for validating the Supplier API implementation
Author: Tiqets Team
Author-email: connections@tiqets.com
Classifier: Programming Language :: Python
Classifier: Programming Language :: Python :: 3
Classifier: Programming Language :: Python :: 3.7
Classifier: Programming Language :: Python :: 3.8
Classifier: Programming Language :: Python :: 3.9
Classifier: Programming Language :: Python :: 3.10
Classifier: Programming Language :: Python :: 3.11
Classifier: Programming Language :: Python :: 3.12
Classifier: Programming Language :: Python :: 3.13
Classifier: License :: OSI Approved :: MIT License
Classifier: Operating System :: OS Independent
Requires-Python: >=3.7
Requires-Dist: requests ==2.32.3
Requires-Dist: dacite ==1.8.1
Requires-Dist: clickclick ==20.10.2
